pyKannada/__init__.py
pyKannada/__main__.py
pyKannada/kannada_keywords.py
pyKannada/main.py
pyKannada-1.0.dist-info/METADATA
pyKannada-1.0.dist-info/WHEEL
pyKannada-1.0.dist-info/entry_points.txt
pyKannada-1.0.dist-info/top_level.txt
pyKannada-1.0.dist-info/RECORD
