Metadata-Version: 2.1
Name: pyKannada
Version: 1.0
Summary: Python in Kannada
Home-page: https://github.com/mithun50/pyKannada
Author: MithunGowda.B, Manvanth.
Author-email: mithungowda.b7411@gmail.com, appuka1431@gmail.com
Keywords: This is the PyPi Module which give the user to write The Python in Kannada
Classifier: Programming Language :: Python :: 3
Classifier: Programming Language :: Python :: 3.6
Classifier: Programming Language :: Python :: 3.7
Classifier: Programming Language :: Python :: 3.8
Classifier: Programming Language :: Python :: 3.9
Classifier: License :: OSI Approved :: MIT License
Classifier: Operating System :: OS Independent
Classifier: Intended Audience :: Developers
Classifier: Topic :: Software Development :: Libraries :: Python Modules
Requires-Python: >=3.6
Requires-Dist: requests
